dxf_ruler_generator.py
dxf_ruler_generator-0.0.4.dist-info/LICENSE
dxf_ruler_generator-0.0.4.dist-info/METADATA
dxf_ruler_generator-0.0.4.dist-info/WHEEL
dxf_ruler_generator-0.0.4.dist-info/entry_points.txt
dxf_ruler_generator-0.0.4.dist-info/top_level.txt
dxf_ruler_generator-0.0.4.dist-info/RECORD
