Metadata-Version: 2.1
Name: dxf-ruler-generator
Version: 0.0.4
Summary: Custom sized rulers for digital fabrication.
Home-page: https://github.com/umluizlima/dxf-ruler-generator
Author: Luiz Lima
Author-email: umluizlima@gmail.com
License: MIT License
Platform: UNKNOWN
Classifier: Programming Language :: Python :: 3
Classifier: License :: OSI Approved :: MIT License
Classifier: Operating System :: OS Independent
Requires-Python: >=3.6.0
Requires-Dist: ezdxf
